simple_config_builder/__about__.py
simple_config_builder/__init__.py
simple_config_builder/__main__.py
simple_config_builder/config.py
simple_config_builder/config_io.py
simple_config_builder/config_types.py
simple_config_builder/configparser.py
simple_config_builder/utils.py
simple_config_builder/cli/__init__.py
simple_config_builder/gui_backend/__init__.py
simple_config_builder/gui_backend/api.py
simple_config_builder/gui_backend/favicon.ico
simple_config_builder/gui_backend/session_data.py
simple_config_builder-1.6.0.dist-info/METADATA
simple_config_builder-1.6.0.dist-info/WHEEL
simple_config_builder-1.6.0.dist-info/entry_points.txt
simple_config_builder-1.6.0.dist-info/licenses/LICENSE.txt
simple_config_builder-1.6.0.dist-info/RECORD
