Metadata-Version: 2.4
Name: simple_config_builder
Version: 1.6.0
Project-URL: Documentation, https://jogehl.github.io/config
Project-URL: Issues, https://github.com/jogehl/config/issues
Project-URL: Source, https://github.com/jogehl/config
Author-email: "Gehlen, Joshua" <joshuagehlen@hotmail.com>
License-Expression: MIT
License-File: LICENSE.txt
Classifier: Development Status :: 1 - Planning
Classifier: Programming Language :: Python
Classifier: Programming Language :: Python :: 3.12
Classifier: Programming Language :: Python :: Implementation :: CPython
Classifier: Programming Language :: Python :: Implementation :: PyPy
Requires-Python: >=3.12
Requires-Dist: click
Requires-Dist: fastapi[all]
Requires-Dist: pyaml
Requires-Dist: pydantic
Requires-Dist: toml
Provides-Extra: docs
Requires-Dist: mike; extra == 'docs'
Requires-Dist: mkdocs; extra == 'docs'
Requires-Dist: mkdocs-autorefs; extra == 'docs'
Requires-Dist: mkdocs-include-markdown-plugin; extra == 'docs'
Requires-Dist: mkdocs-material; extra == 'docs'
Requires-Dist: mkdocs-material-extensions; extra == 'docs'
Requires-Dist: mkdocstrings[python]; extra == 'docs'
